{
  "patient_id": "patient_02",
  "conditions": [
    "Acute appendicitis"
  ],
  "medications": [
    {
      "name": "Ceftriaxone",
      "dose": "1 g",
      "route": "IV",
      "when": "pre-op"
    },
    {
      "name": "Metronidazole",
      "dose": "500 mg",
      "route": "IV",
      "when": "pre-op"
    },
    {
      "name": "Acetaminophen",
      "dose": "650 mg",
      "route": "PO",
      "when": "q6h PRN pain"
    }
  ],
  "observations": [
    {
      "name": "Temperature",
      "value": "38.1 C"
    },
    {
      "name": "White Blood Cell Count",
      "value": "14.2 K/uL"
    }
  ],
  "procedures": [
    {
      "name": "Laparoscopic appendectomy",
      "date": "2026-03-18"
    }
  ]
}